pydata_sphinx_theme/__init__.py
pydata_sphinx_theme/assets/scripts/bootstrap.js
pydata_sphinx_theme/assets/scripts/mixin.js
pydata_sphinx_theme/assets/scripts/pydata-sphinx-theme.js
pydata_sphinx_theme/assets/styles/abstracts/_mixins.scss
pydata_sphinx_theme/assets/styles/base/_base.scss
pydata_sphinx_theme/assets/styles/bootstrap.scss
pydata_sphinx_theme/assets/styles/components/_breadcrumbs.scss
pydata_sphinx_theme/assets/styles/components/_icon-links.scss
pydata_sphinx_theme/assets/styles/components/_indices.scss
pydata_sphinx_theme/assets/styles/components/_navbar-links.scss
pydata_sphinx_theme/assets/styles/components/_page-toc.scss
pydata_sphinx_theme/assets/styles/components/_prev-next.scss
pydata_sphinx_theme/assets/styles/components/_readthedocs-switcher.scss
pydata_sphinx_theme/assets/styles/components/_search.scss
pydata_sphinx_theme/assets/styles/components/_searchbox.scss
pydata_sphinx_theme/assets/styles/components/_switcher-theme.scss
pydata_sphinx_theme/assets/styles/components/_switcher-version.scss
pydata_sphinx_theme/assets/styles/components/_toc-inpage.scss
pydata_sphinx_theme/assets/styles/components/_versionmodified.scss
pydata_sphinx_theme/assets/styles/components/header/_header-logo.scss
pydata_sphinx_theme/assets/styles/content/_admonitions.scss
pydata_sphinx_theme/assets/styles/content/_api.scss
pydata_sphinx_theme/assets/styles/content/_code.scss
pydata_sphinx_theme/assets/styles/content/_figures.scss
pydata_sphinx_theme/assets/styles/content/_footnotes.scss
pydata_sphinx_theme/assets/styles/content/_hacks.scss
pydata_sphinx_theme/assets/styles/content/_lists.scss
pydata_sphinx_theme/assets/styles/content/_math.scss
pydata_sphinx_theme/assets/styles/content/_quotes.scss
pydata_sphinx_theme/assets/styles/content/_spans.scss
pydata_sphinx_theme/assets/styles/content/_tables.scss
pydata_sphinx_theme/assets/styles/content/_toctree.scss
pydata_sphinx_theme/assets/styles/extensions/_ablog.scss
pydata_sphinx_theme-0.13.2.dist-info/LICENSE
pydata_sphinx_theme-0.13.2.dist-info/METADATA
pydata_sphinx_theme-0.13.2.dist-info/WHEEL
pydata_sphinx_theme-0.13.2.dist-info/entry_points.txt
pydata_sphinx_theme-0.13.2.dist-info/RECORD