Metadata-Version: 2.1
Name: pydata-sphinx-theme
Version: 0.13.2
Summary: Bootstrap-based Sphinx theme from the PyData community
Maintainer-Email: Joris Van den Bossche <jorisvandenbossche@gmail.com>
License: BSD 3-Clause License
Classifier: Development Status :: 5 - Production/Stable
Classifier: Programming Language :: Python :: 3
Classifier: Programming Language :: Python :: 3.7
Classifier: Programming Language :: Python :: 3.8
Classifier: Programming Language :: Python :: 3.9
Classifier: Programming Language :: Python :: 3.10
Classifier: Programming Language :: Python :: 3.11
Classifier: Framework :: Sphinx
Classifier: Framework :: Sphinx :: Theme
Classifier: License :: OSI Approved :: BSD License
Classifier: Operating System :: OS Independent
Requires-Python: >=3.7
Requires-Dist: sphinx>=4.2
Requires-Dist: beautifulsoup4
Requires-Dist: docutils!=0.17.0
Requires-Dist: packaging
Requires-Dist: Babel
Requires-Dist: pygments>=2.7
Requires-Dist: accessible-pygments
Requires-Dist: numpydoc; extra == "doc"
Requires-Dist: myst-nb; extra == "doc"
Requires-Dist: linkify-it-py; extra == "doc"
Requires-Dist: rich; extra == "doc"
Requires-Dist: sphinxext-rediraffe; extra == "doc"
Requires-Dist: sphinx-sitemap; extra == "doc"
Requires-Dist: ablog>=0.11.0rc2; extra == "doc"
Requires-Dist: jupyter_sphinx; extra == "doc"
Requires-Dist: pandas; extra == "doc"
Requires-Dist: plotly; extra == "doc"
Requires-Dist: matplotlib; extra == "doc"
Requires-Dist: numpy; extra == "doc"
Requires-Dist: xarray; extra == "doc"
Requires-Dist: sphinx-copybutton; extra == "doc"
Requires-Dist: sphinx-design; extra == "doc"
Requires-Dist: sphinx-togglebutton; extra == "doc"
Requires-Dist: sphinxcontrib-youtube; extra == "doc"
Requires-Dist: sphinx-favicon>=1.0.1; extra == "doc"
Requires-Dist: nbsphinx; extra == "doc"
Requires-Dist: ipyleaflet; extra == "doc"
Requires-Dist: colorama; extra == "doc"
Requires-Dist: pytest; extra == "test"
Requires-Dist: pytest-cov; extra == "test"
Requires-Dist: pytest-regressions; extra == "test"
Requires-Dist: codecov; extra == "test"
Requires-Dist: pyyaml; extra == "dev"
Requires-Dist: pre-commit; extra == "dev"
Requires-Dist: nox; extra == "dev"
Requires-Dist: pydata-sphinx-theme[doc,test]; extra == "dev"
Provides-Extra: doc
Provides-Extra: test
Provides-Extra: dev
